displayarray/__init__.py
displayarray/__main__.py
displayarray/_uid.py
displayarray/_util.py
displayarray/callbacks.py
displayarray/input.py
displayarray/effects/__init__.py
displayarray/effects/crop.py
displayarray/effects/lens.py
displayarray/effects/overlay.py
displayarray/effects/select_channels.py
displayarray/effects/transform.py
displayarray/frame/__init__.py
displayarray/frame/frame_publishing.py
displayarray/frame/frame_updater.py
displayarray/frame/get_frame_ids.py
displayarray/frame/np_to_opencv.py
displayarray/frame/subscriber_dictionary.py
displayarray/frame/zmq_to_opencv.py
displayarray/window/__init__.py
displayarray/window/subscriber_windows.py
displayarray/window/window_commands.py
displayarray-1.3.1.dist-info/LICENSE.md
displayarray-1.3.1.dist-info/METADATA
displayarray-1.3.1.dist-info/WHEEL
displayarray-1.3.1.dist-info/entry_points.txt
displayarray-1.3.1.dist-info/top_level.txt
displayarray-1.3.1.dist-info/RECORD
