Metadata-Version: 2.1
Name: displayarray
Version: 1.3.1
Summary: Tool for displaying numpy arrays.
Home-page: UNKNOWN
Author: SimLeek
Author-email: simulator.leek@gmail.com
License: MIT
Project-URL: repository, https://github.com/simleek/displayarray
Platform: UNKNOWN
Requires-Python: ==3.*,>=3.7.0
Requires-Dist: docopt (==0.6.2)
Requires-Dist: localpubsub (==0.0.4)
Requires-Dist: numpy (>=1.14.5)
Requires-Dist: opencv-python (==4.*,>=4.0.0)
Requires-Dist: pyzmq (>=22.0.3)
Requires-Dist: tensorcom
Provides-Extra: dev
Requires-Dist: black (==18.*,>=18.3.0.a0) ; extra == 'dev'
Requires-Dist: coverage (==4.*,>=4.5.0) ; extra == 'dev'
Requires-Dist: mock (==3.*,>=3.0.0) ; extra == 'dev'
Requires-Dist: mypy (==0.*,>=0.740.0) ; extra == 'dev'
Requires-Dist: pydocstyle (==4.*,>=4.0.0) ; extra == 'dev'
Requires-Dist: pytest (==5.2.1) ; extra == 'dev'
Requires-Dist: sphinx (==2.*,>=2.2.0) ; extra == 'dev'
Requires-Dist: tox (==3.*,>=3.14.0) ; extra == 'dev'
Requires-Dist: tox-gh-actions (==0.*,>=0.3.0) ; extra == 'dev'
Requires-Dist: typing (==3.7.4.1) ; extra == 'dev'
Requires-Dist: wheel (==0.*,>=0.30.0) ; extra == 'dev'
